safetypes/__init__.py
safetypes/base/SafeFiles.py
safetypes/base/SafeFunctionTypes.py
safetypes/base/__init__.py
safetypes-0.1rc2.post4.dist-info/LICENSE
safetypes-0.1rc2.post4.dist-info/METADATA
safetypes-0.1rc2.post4.dist-info/WHEEL
safetypes-0.1rc2.post4.dist-info/top_level.txt
safetypes-0.1rc2.post4.dist-info/RECORD
