Metadata-Version: 2.1
Name: safetypes
Version: 0.1rc2.post4
Summary: Python is a not typed language, and runs under the paradigm of first try and then it success or fails. This package allows you to have the capability of apply typing features in last versions of Python, allowing to the developer to have a transparent mechanism to grant that typing annotations are satisfied in the execution time of their programs.
Home-page: https://github.com/wiscot/safetypes
Author: Rafael Gutiérrez Martínez
Author-email: Rafael Gutiérrez Martínez <ragutimar@gmail.com>
License: MIT License
Project-URL: Homepage, https://github.com/wiscot/safetypes
Project-URL: Bug Tracker, https://github.com/wiscot/safetypes/issues
Classifier: Programming Language :: Python :: 3
Classifier: License :: OSI Approved :: MIT License
Classifier: Operating System :: OS Independent
Classifier: Intended Audience :: Developers
Classifier: Intended Audience :: Information Technology
Classifier: Intended Audience :: Science/Research
Classifier: Topic :: Education :: Testing
Classifier: Topic :: Scientific/Engineering
Classifier: Topic :: Software Development
Classifier: Topic :: Software Development :: Debuggers
Classifier: Typing :: Typed
Requires-Python: >=3.5
License-File: LICENSE
